BST/AVLTree.py
BST/AVLTreeDemo.py
BST/binarySearchTree.py
BST/binarySearchTreeDemo.py
DS/BST/AVLTree.py
DS/BST/AVLTreeDemo.py
DS/BST/binarySearchTree.py
DS/BST/binarySearchTreeDemo.py
DS/hashTable_/chainedHashTable.py
DS/hashTable_/chainedHashTableDemo.py
DS/hashTable_/hashOpenAddressed.py
DS/hashTable_/hashOpenAddressedDemo.py
DS/hashTable_/listHashTable.py
DS/hashTable_/listHashTableDemo.py
DS/heap_/heap.py
DS/heap_/heapDemo.py
DS/list_/__init__.py
DS/list_/bidirectNode.py
DS/list_/circularDoublyLinkedList.py
DS/list_/circularDoublyLinkedListDemo.py
DS/list_/circularLinkedList.py
DS/list_/circularLinkedListDemo.py
DS/list_/linkedListBasic.py
DS/list_/linkedListBasicDemo.py
DS/list_/listNode.py
DS/queue_/linkedQueue.py
DS/queue_/linkedQueueDemo.py
DS/queue_/listQueue.py
DS/queue_/listQueueDemo.py
DS/queue_/palindrome.py
DS/sort_/bubbleSort.py
DS/sort_/bubbleSortDemo.py
DS/sort_/bucketSort.py
DS/sort_/bucketSortDemo.py
DS/sort_/countingSort.py
DS/sort_/countingSortDemo.py
DS/sort_/heapSort.py
DS/sort_/heapSortDemo.py
DS/sort_/insertionSort.py
DS/sort_/insertionSortDemo.py
DS/sort_/mergeSort.py
DS/sort_/mergeSortDemo.py
DS/sort_/quickSort.py
DS/sort_/quickSortDemo.py
DS/sort_/radixSort.py
DS/sort_/radixSortDemo.py
DS/sort_/selectionSort.py
DS/sort_/selectionSortDemo.py
DS/sort_/shellSort.py
DS/sort_/shellSortDemo.py
DS/stack_/linkedStack.py
DS/stack_/linkedStackDemo.py
DS/stack_/listStack.py
DS/stack_/listStackDemo.py
DS/stack_/postfix.py
DS/stack_/reverseString.py
hashTable/chainedHashTable.py
hashTable/chainedHashTableDemo.py
hashTable/hashOpenAddressed.py
hashTable/hashOpenAddressedDemo.py
hashTable/listHashTable.py
hashTable/listHashTableDemo.py
hashTable_/chainedHashTable.py
hashTable_/chainedHashTableDemo.py
hashTable_/hashOpenAddressed.py
hashTable_/hashOpenAddressedDemo.py
hashTable_/listHashTable.py
hashTable_/listHashTableDemo.py
heap_/heap.py
heap_/heapDemo.py
list/__init__.py
list/bidirectNode.py
list/circularDoublyLinkedList.py
dsdau-0.0.1.3.dist-info/LICENSE
dsdau-0.0.1.3.dist-info/METADATA
dsdau-0.0.1.3.dist-info/WHEEL
dsdau-0.0.1.3.dist-info/top_level.txt
dsdau-0.0.1.3.dist-info/RECORD
