Metadata-Version: 2.1
Name: dsdau
Version: 0.0.1.3
Summary: DAU Data Structure Modules
Home-page: https://github.com/jsk0910/DAU_DS
Download-URL: https://github.com/jsk0910/DAU_DS/archive/refs/tags/v0.0.1.3.zip
Author: SangKyunJeon
Author-email: sangkyun.jeon@gmail.com
Classifier: Programming Language :: Python :: 3
Classifier: Operating System :: OS Independent
License-File: LICENSE
Requires-Dist: pytest
